ccbcge/__init__.py
ccbcge/dataAccess.py
ccbcge/version.py
ccbcge-0.1.3.dist-info/LICENSE
ccbcge-0.1.3.dist-info/METADATA
ccbcge-0.1.3.dist-info/WHEEL
ccbcge-0.1.3.dist-info/top_level.txt
ccbcge-0.1.3.dist-info/RECORD
