Metadata-Version: 2.1
Name: ccbcge
Version: 0.1.3
Summary: A package to access gene expression data for breast cancer
Author: Bryce Tolman
Author-email: bat.2000@live.com
License: Apache-2.0
Project-URL: Homepage, https://github.com/brycetolman54/ccbcge
Keywords: gene expression,breast cancer,bioinformatics
Classifier: Programming Language :: Python :: 3
Classifier: License :: OSI Approved :: Apache Software License
Requires-Python: >=3.8
License-File: LICENSE
Requires-Dist: requests>2.25.1
Requires-Dist: pandas>1.3.0
